Metadata-Version: 2.2
Name: openai_commands
Version: 3.250.1
Summary: 🛠️ a command interface to the OpenAI API.
Home-page: https://github.com/kamangir/openai-commands
Author: Arash Abadpour (Kamangir)
Author-email: arash@kamangir.net
License: Public Domain
Classifier: Programming Language :: Python :: 3
Classifier: Programming Language :: Unix Shell
Classifier: License :: Public Domain
Classifier: Operating System :: OS Independent
License-File: LICENSE
Requires-Dist: blueness
Requires-Dist: abcli
Requires-Dist: blueflow
Requires-Dist: IPython
Requires-Dist: beautifulsoup4
Requires-Dist: boto3
Requires-Dist: bs4
Requires-Dist: Flask
Requires-Dist: folium
Requires-Dist: geojson
Requires-Dist: geopandas
Requires-Dist: matplotlib
Requires-Dist: openai
Requires-Dist: opencv-python
Requires-Dist: pymysql
Requires-Dist: pyyaml
Requires-Dist: pylint
Requires-Dist: pytest
Requires-Dist: python-dotenv[cli]
Requires-Dist: requests
Requires-Dist: scikit-image
Requires-Dist: tqdm
Dynamic: author
Dynamic: author-email
Dynamic: classifier
Dynamic: description
Dynamic: description-content-type
Dynamic: home-page
Dynamic: license
Dynamic: requires-dist
Dynamic: summary
